2_SIM/1_TASK/1_LOGIC_CIRCUIT/2_Seq_logic/14_FSM/seq_detector.v
`timescale 1ns / 1ps  
module seq_detector (
                 i_x    ,
                 i_Clk  ,
                 i_nRst ,
                 o_y
);

     input       i_x    ;
     input       i_Clk  ;
     input       i_nRst ;
     output      o_y    ;

     localparam  S0 = 2'b00     ;
     localparam  S1 = 2'b01     ;
     localparam  S2 = 2'b11     ;
     localparam  S3 = 2'b10     ;

     reg [1:0]   r_state, r_next;
     
     always @(posedge i_Clk or negedge i_nRst) begin
        if (!i_nRst) r_state <= S0     ;
        else         r_state <= r_next ;
     end

     always @(*) begin
         case (r_state)
         S0 : if (i_x) r_next = S1; else r_next = S0;
         S1 : if (i_x) r_next = S2; else r_next = S0;
         S2 : if (i_x) r_next = S3; else r_next = S0;
         S3 : if (i_x) r_next = S3; else r_next = S0;
         endcase
     end

     reg     o_y;
     always @(*) begin
         if (r_state == S3) o_y = 1'b1;
         else               o_y = 1'b0;
         
     end
endmodule

2_SIM/1_TASK/1_LOGIC_CIRCUIT/2_Seq_logic/14_FSM/tb_seq_detector.v
`timescale 1ns / 1ps
module tb_seq_detector;

        // DUT 입력에 연결할 reg, 출력에 연결할 wire
        reg     t_x     ;
        reg     t_Clk   ;
        reg     t_nRst  ;
        wire    t_y     ;

        // DUT (Device Under Test) 인스턴스
        seq_detector dut (
                .i_x    ( t_x    ),
                .i_Clk  ( t_Clk  ),
                .i_nRst ( t_nRst ),
                .o_y    ( t_y    )
        );

        // 클럭 생성 : 10ns 주기 (posedge는 5,15,25... ns)
        initial begin
                t_Clk = 1'b0 ;
                forever #5 t_Clk = ~t_Clk ;
        end

        // 자극(stimulus) 인가
        // ※ FSM 시퀀스 검출기: 1이 3개 이상 연속이면 y=1 (Moore)
        //    S0(초기) -> S1(1개) -> S2(2개) -> S3(3개+, y=1)
        //    0이 들어오면 -> S0으로 (초기화)
        initial begin
                // 비동기 리셋으로 초기화 (S0)
                t_nRst = 1'b0 ; t_x = 1'b0 ;
                #12 ;
                t_nRst = 1'b1 ;

                // 케이스 1: 1을 1개만 -> y 안 뜸
                t_x = 1'b1 ; #10 ;      // S0->S1
                t_x = 1'b0 ; #10 ;      // S1->S0 (끊김)

                // 케이스 2: 1을 2개 -> y 안 뜸
                t_x = 1'b1 ; #10 ;      // S0->S1
                t_x = 1'b1 ; #10 ;      // S1->S2
                t_x = 1'b0 ; #10 ;      // S2->S0 (끊김)

                // 케이스 3: 1을 3개 연속 -> y=1 (핵심)
                t_x = 1'b1 ; #10 ;      // S0->S1
                t_x = 1'b1 ; #10 ;      // S1->S2
                t_x = 1'b1 ; #10 ;      // S2->S3 (y=1 여기서)
                t_x = 1'b0 ; #10 ;      // S3->S0

                // 케이스 4: 1을 5개 연속 -> y=1 계속 유지
                t_x = 1'b1 ; #10 ;      // S0->S1
                t_x = 1'b1 ; #10 ;      // S1->S2
                t_x = 1'b1 ; #10 ;      // S2->S3 (y=1 시작)
                t_x = 1'b1 ; #10 ;      // S3->S3 (y=1 유지)
                t_x = 1'b1 ; #10 ;      // S3->S3 (y=1 유지)
                t_x = 1'b0 ; #10 ;      // S3->S0 (끊김)

                // 케이스 5: 동작 중 비동기 리셋
                t_x = 1'b1 ; #10 ;      // S0->S1
                t_x = 1'b1 ; #10 ;      // S1->S2
                #3 ;
                t_nRst = 1'b0 ;         // 리셋 -> 즉시 S0 (y=0)
                #6 ;
                t_nRst = 1'b1 ;

                // 리셋 후 다시 3개 연속
                t_x = 1'b1 ; #10 ;
                t_x = 1'b1 ; #10 ;
                t_x = 1'b1 ; #10 ;      // y=1

                t_x = 1'b0 ; #10 ;

                $finish ;
        end

        // 콘솔 모니터링 (상태도 같이 보이도록)
        initial begin
                $monitor("time=%0t | nRst=%b x=%b state=%b | y=%b",
                          $time, t_nRst, t_x, dut.r_state, t_y);
        end

        // 파형 덤프
        initial begin
                $dumpfile("tb_seq_detector.vcd");
                $dumpvars(0, tb_seq_detector);
        end

endmodule

2_SIM/1_TASK/1_LOGIC_CIRCUIT/2_Seq_logic/14_FSM/tb_seq_detector.vcd
$date
    Aug 18, 2026  10:22:34
$end
$version
    TOOL:	xmsim(64)	22.03-s012
$end
$timescale
    1 ps
$end

$scope module tb_seq_detector $end
$var reg       1 !    t_x $end
$var reg       1 "    t_Clk $end
$var reg       1 #    t_nRst $end
$var wire      1 $    t_y  $end

$scope module dut $end
$var wire      1 %    i_x  $end
$var wire      1 &    i_Clk  $end
$var wire      1 '    i_nRst  $end
$var reg       1 (    o_y $end
$var parameter  2 )    S0 $end
$var parameter  2 *    S1 $end
$var parameter  2 +    S2 $end
$var parameter  2 ,    S3 $end
$var reg       2 -    r_state [1:0] $end
$var reg       2 .    r_next [1:0] $end
$upscope $end

$upscope $end

$enddefinitions $end
$dumpvars
b10 ,
b11 +
b1 *
b0 )
0!
0"
0#
0$
0%
0&
0'
0(
b0 -
b0 .
$end
#5000
1"
1&
#10000
0"
0&
#12000
1#
1!
1%
1'
b1 .
#15000
1"
1&
b1 -
b11 .
#20000
0"
0&
#22000
0!
0%
b0 .
#25000
1"
1&
b0 -
#30000
0"
0&
#32000
1!
1%
b1 .
#35000
1"
1&
b1 -
b11 .
#40000
0"
0&
#45000
1"
1&
b11 -
b10 .
#50000
0"
0&
#52000
0!
0%
b0 .
#55000
1"
1&
b0 -
#60000
0"
0&
#62000
1!
1%
b1 .
#65000
1"
1&
b1 -
b11 .
#70000
0"
0&
#75000
1"
1&
b11 -
b10 .
#80000
0"
0&
#85000
1"
1&
b10 -
1(
1$
#90000
0"
0&
#92000
0!
0%
b0 .
#95000
1"
1&
b0 -
0(
0$
#100000
0"
0&
#102000
1!
1%
b1 .
#105000
1"
1&
b1 -
b11 .
#110000
0"
0&
#115000
1"
1&
b11 -
b10 .
#120000
0"
0&
#125000
1"
1&
b10 -
1(
1$
#130000
0"
0&
#135000
1"
1&
#140000
0"
0&
#145000
1"
1&
#150000
0"
0&
#152000
0!
0%
b0 .
#155000
1"
1&
b0 -
0(
0$
#160000
0"
0&
#162000
1!
1%
b1 .
#165000
1"
1&
b1 -
b11 .
#170000
0"
0&
#175000
1"
1&
b11 -
b10 .
#180000
0"
0&
#185000
1"
0#
0'
1&
b0 -
b1 .
#190000
0"
0&
#191000
1#
1'
#195000
1"
1&
b1 -
b11 .
#200000
0"
0&
#205000
1"
1&
b11 -
b10 .
#210000
0"
0&
#215000
1"
1&
b10 -
1(
1$
#220000
0"
0&
#221000
0!
0%
b0 .
#225000
1"
1&
b0 -
0(
0$
