2_SIM/1_TASK/1_LOGIC_CIRCUIT/2_Seq_logic/14_FSM/seq_detector.v
`timescale 1ns / 1ps  
module seq_detector (
                 i_x    ,
                 i_Clk  ,
                 i_nRst ,
                 o_y
);

     input       i_x    ;
     input       i_Clk  ;
     input       i_nRst ;
     output      o_y    ;

     localparam  S0 = 2'b00     ;
     localparam  S1 = 2'b01     ;
     localparam  S2 = 2'b11     ;
     localparam  S3 = 2'b10     ;

     reg [1:0]   r_state, r_next;
     
     always @(posedge i_Clk or negedge i_nRst) begin
        if (!i_nRst) r_state <= S0     ;
        else         r_state <= r_next ;
     end

     always @(*) begin
         case (r_state)
         S0 : if (i_x) r_next = S1; else r_next = S0;
         S1 : if (i_x) r_next = S2; else r_next = S0;
         S2 : if (i_x) r_next = S3; else r_next = S0;
         S3 : if (i_x) r_next = S3; else r_next = S0;
         endcase
     end

     reg     o_y;
     always @(*) begin
         if (r_state == S3) o_y = 1'b1;
         else               o_y = 1'b0;
         
     end
endmodule

2_SIM/1_TASK/1_LOGIC_CIRCUIT/2_Seq_logic/14_FSM/tb_seq_detector.v
`timescale 1ns / 1ps
module tb_seq_detector;

        reg     t_x    ;
        reg     t_Clk  ;
        reg     t_nRst ;
        wire    t_y    ;

        seq_detector dut (
                .i_x    ( t_x    ),
                .i_Clk  ( t_Clk  ),
                .i_nRst ( t_nRst ),
                .o_y    ( t_y    )
        );

        initial begin
                t_Clk = 1'b0 ;
                forever #5 t_Clk = ~t_Clk ;
        end

        initial begin
                t_nRst = 1'b0 ; t_x = 1'b0 ; #12 ;
                t_nRst = 1'b1 ;

                t_x = 1'b1 ; #10 ;   // S0->S1
                t_x = 1'b1 ; #10 ;   // S1->S2
                t_x = 1'b1 ; #10 ;   // S2->S3, y=1
                t_x = 1'b1 ; #10 ;   // S3->S3, y=1 

                t_x = 1'b0 ; #10 ;   // S3->S0

                t_x = 1'b1 ; #10 ;   // S0->S1
                t_x = 1'b1 ; #10 ;   // S1->S2
                t_x = 1'b1 ; #10 ;   // S2->S3, y=1

                t_x = 1'b0 ; #10 ;   // S3->S0
                $finish ;
        end

        initial begin
                $monitor("time=%0t | nRst=%b x=%b state=%b | y=%b",
                          $time, t_nRst, t_x, dut.r_state, t_y);
        end

        initial begin
                $dumpfile("tb_seq_detector.vcd");
                $dumpvars(0, tb_seq_detector);
        end

endmodule

2_SIM/1_TASK/1_LOGIC_CIRCUIT/2_Seq_logic/14_FSM/tb_seq_detector.vcd
$date
    Aug 18, 2026  20:14:50
$end
$version
    TOOL:	xmsim(64)	22.03-s012
$end
$timescale
    1 ps
$end

$scope module tb_seq_detector $end
$var reg       1 !    t_x $end
$var reg       1 "    t_Clk $end
$var reg       1 #    t_nRst $end
$var wire      1 $    t_y  $end

$scope module dut $end
$var wire      1 %    i_x  $end
$var wire      1 &    i_Clk  $end
$var wire      1 '    i_nRst  $end
$var reg       1 (    o_y $end
$var parameter  2 )    S0 $end
$var parameter  2 *    S1 $end
$var parameter  2 +    S2 $end
$var parameter  2 ,    S3 $end
$var reg       2 -    r_state [1:0] $end
$var reg       2 .    r_next [1:0] $end
$upscope $end

$upscope $end

$enddefinitions $end
$dumpvars
b10 ,
b11 +
b1 *
b0 )
0!
0"
0#
0$
0%
0&
0'
0(
b0 -
b0 .
$end
#5000
1"
1&
#10000
0"
0&
#12000
1#
1!
1%
1'
b1 .
#15000
1"
1&
b1 -
b11 .
#20000
0"
0&
#25000
1"
1&
b11 -
b10 .
#30000
0"
0&
#35000
1"
1&
b10 -
1(
1$
#40000
0"
0&
#45000
1"
1&
#50000
0"
0&
#52000
0!
0%
b0 .
#55000
1"
1&
b0 -
0(
0$
#60000
0"
0&
#62000
1!
1%
b1 .
#65000
1"
1&
b1 -
b11 .
#70000
0"
0&
#75000
1"
1&
b11 -
b10 .
#80000
0"
0&
#85000
1"
1&
b10 -
1(
1$
#90000
0"
0&
#92000
0!
0%
b0 .
#95000
1"
1&
b0 -
0(
0$
