1_RTL/4_COMB_LOGIC/3_DECODER/bcd_to_7seg.v
`timescale 1ns / 1ps

module bcd_to_7seg(
	i_bcd,
	o_seg

);

input 	[3:0] i_bcd	;
output	[6:0] o_seg	;

reg	[6:0] o_seg	;
always @(i_bcd) begin
	case (i_bcd)
		4'b0000: o_seg = 7'b1111110; //0
		4'b0001: o_seg = 7'b0110000; //1
		4'b0010: o_seg = 7'b1101101; //2
		4'b0011: o_seg = 7'b1111001; //3
		4'b0100: o_seg = 7'b0110011; //4
		4'b0101: o_seg = 7'b1011011; //5
		4'b0110: o_seg = 7'b1011111; //6
		4'b0111: o_seg = 7'b1110000; //7
		4'b1000: o_seg = 7'b1111111; //8
		4'b1001: o_seg = 7'b1111011; //9
		default: o_seg = 7'b0000000; //disabled
	endcase
end

endmodule

1_RTL/4_COMB_LOGIC/3_DECODER/tb_bcd_to_7seg.v
`timescale 1ns / 1ps

module tb_bcd_to_7seg;

reg	[3:0] i_bcd	;
wire	[6:0] o_seg	;

bcd_to_7seg uut (
	.i_bcd(i_bcd),
	.o_seg(o_seg)	

);

initial begin
	$dumpfile("./bcd_to_7seg.vcd"	);
	$dumpvars(0, tb_bcd_to_7seg	);
end

initial begin
	$monitor("Time=%0t | i_bcd Input=%b | Seven Segment Output=%b", $time, i_bcd, o_seg);

	i_bcd = 4'b0000; #10;
	i_bcd = 4'b0001; #10;
	i_bcd = 4'b0010; #10;
	i_bcd = 4'b0011; #10;
	i_bcd = 4'b0100; #10;
	i_bcd = 4'b0101; #10;
	i_bcd = 4'b0110; #10;
	i_bcd = 4'b0111; #10;
	i_bcd = 4'b1000; #10;
	i_bcd = 4'b1001; #10;

	$finish;
end

endmodule

1_RTL/4_COMB_LOGIC/3_DECODER/bcd_to_7seg.vcd
$date
    Jul  1, 2026  19:25:43
$end
$version
    TOOL:	xmsim(64)	22.03-s012
$end
$timescale
    1 ps
$end

$scope module tb_bcd_to_7seg $end
$var reg       4 !    i_bcd [3:0] $end
$var wire      7 "    o_seg [6:0] $end

$scope module uut $end
$var wire      4 #    i_bcd [3:0] $end
$var reg       7 $    o_seg [6:0] $end
$upscope $end

$upscope $end

$enddefinitions $end
$dumpvars
b0 !
b1111110 "
b0 #
b1111110 $
$end
#10000
b1 !
b1 #
b110000 $
b110000 "
#20000
b10 !
b10 #
b1101101 $
b1101101 "
#30000
b11 !
b11 #
b1111001 $
b1111001 "
#40000
b100 !
b100 #
b110011 $
b110011 "
#50000
b101 !
b101 #
b1011011 $
b1011011 "
#60000
b110 !
b110 #
b1011111 $
b1011111 "
#70000
b111 !
b111 #
b1110000 $
b1110000 "
#80000
b1000 !
b1000 #
b1111111 $
b1111111 "
#90000
b1001 !
b1001 #
b1111011 $
b1111011 "
