1_RTL/1_TASK/1_LOGIC_CIRCUIT/2_Seq_logic/5_Master_slave_DFF/d_ff_ms_3.v
`timescale 1ns / 1ps  
module d_ff_ms_3 ( // nededge trigger
                   i_D   ,
                   i_clk ,
                   o_Q  
);
       input       i_D   ;
       input       i_clk ;
       output      o_Q   ;
    
       reg         o_Q   ;   
    
       always@(negedge i_clk) begin
                   o_Q <= i_D ; // F/F은 non-blocking
       end
endmodule

2_SIM/1_TASK/1_LOGIC_CIRCUIT/2_Seq_logic/5_Master_slave_DFF/tb_d_ff_ms_3.v
`timescale 1ns / 1ps
module tb_d_ff_ms_3;

        // DUT 입력에 연결할 reg, 출력에 연결할 wire
        reg     t_D    ;
        reg     t_clk  ;
        wire    t_Q    ;

        // DUT (Device Under Test) 인스턴스
        d_ff_ms_3 dut (
                .i_D   ( t_D   ),
                .i_clk ( t_clk ),
                .o_Q   ( t_Q   )
        );

        // 클럭 생성 : 10ns 주기 (5ns 마다 반전)
        initial begin
                t_clk = 1'b0 ;
                forever #5 t_clk = ~t_clk ;
        end

        // 자극(stimulus) 인가
        // ※ 이 FF는 negedge(하강 엣지)에서만 D를 Q로 잡음
        //    D를 여러 값으로 바꿔가며, 하강 엣지 순간의 값이 Q에 저장되는지 확인
        initial begin
                t_D = 1'b0 ;
                #12 ;               // 첫 하강엣지(10ns) 지난 후 -> Q=0

                t_D = 1'b1 ;        // D=1
                #10 ;               // 다음 하강엣지(20ns)에서 -> Q=1

                t_D = 1'b0 ;        // D=0
                #10 ;               // 하강엣지(30ns) -> Q=0

                t_D = 1'b1 ;        // D=1
                #3  ;               // 하강엣지 전에 D 바꿈 (엣지 아닌 순간엔 Q 안 바뀜 확인)
                t_D = 1'b0 ;        // 다시 D=0 (엣지 직전 값이 잡힘)
                #7  ;               // 하강엣지(40ns) -> Q=0 (엣지 순간 D=0)

                t_D = 1'b1 ;        // D=1
                #10 ;               // 하강엣지(50ns) -> Q=1

                t_D = 1'b1 ;        // D=1 유지
                #10 ;               // 하강엣지(60ns) -> Q=1 유지

                t_D = 1'b0 ;        // D=0
                #10 ;               // 하강엣지(70ns) -> Q=0

                $finish ;
        end

        // 콘솔 모니터링
        initial begin
                $monitor("time=%0t | clk=%b D=%b | Q=%b",
                          $time, t_clk, t_D, t_Q);
        end

        // 파형 덤프
        initial begin
                $dumpfile("tb_d_ff_ms_3.vcd");
                $dumpvars(0, tb_d_ff_ms_3);
        end

endmodule

2_SIM/1_TASK/1_LOGIC_CIRCUIT/2_Seq_logic/5_Master_slave_DFF/tb_d_ff_ms_3.vcd
$date
    Aug 18, 2026  09:41:45
$end
$version
    TOOL:	xmsim(64)	22.03-s012
$end
$timescale
    1 ps
$end

$scope module tb_d_ff_ms_3 $end
$var reg       1 !    t_D $end
$var reg       1 "    t_clk $end
$var wire      1 #    t_Q  $end

$scope module dut $end
$var wire      1 $    i_D  $end
$var wire      1 %    i_clk  $end
$var reg       1 &    o_Q $end
$upscope $end

$upscope $end

$enddefinitions $end
$dumpvars
0!
0"
0#
0$
0%
0&
$end
#5000
1"
1%
#10000
0"
0%
#12000
1!
1$
#15000
1"
1%
#20000
0"
0%
1&
1#
#22000
0!
0$
#25000
1"
1%
#30000
0"
0%
0&
0#
#32000
1!
1$
#35000
1"
0!
0$
1%
#40000
0"
0%
#42000
1!
1$
#45000
1"
1%
#50000
0"
0%
1&
1#
#55000
1"
1%
#60000
0"
0%
#62000
0!
0$
#65000
1"
1%
#70000
0"
0%
0&
0#
