1_RTL/2_TINY_PROJECT/counter6_down.v
`timescale 1ns /1ps

module counter6_down (
	clk	,
	rst_n	,
	i_en	,
	o_count
);

	input		clk	;
	input		rst_n	;
	input		i_en	;
	output	[2:0]	o_count	;

	reg 	[2:0]	o_count	;
	
	always @(posedge clk) begin
		if (!rst_n)
			o_count <= 3'd5;
		else if (i_en)	
			case (o_count)
				3'd5 	: o_count <= o_count - 3'd1	;
				3'd4 	: o_count <= o_count - 3'd1	;
				3'd3 	: o_count <= o_count - 3'd1	;
				3'd2 	: o_count <= o_count - 3'd1	;
				3'd1 	: o_count <= o_count - 3'd1	;
				default	: o_count <= 3'd5		;
			endcase 
	end

endmodule

1_RTL/2_TINY_PROJECT/tb_counter6_down.v
`timescale 1ns / 1ps

module tb_counter6_down;

	reg		clk	;
	reg		rst_n	;
	reg		i_en	;
	wire	[2:0]	o_count	;

	counter6_down dut(
		.clk		(clk		),
		.rst_n		(rst_n		),
		.i_en		(i_en		),
		.o_count	(o_count	)
			);

	always #5 clk = ~clk;

	initial begin
		clk		= 1'b0		;
		rst_n		= 1'b0		;
		i_en		= 1'b0		;
		#20 	rst_n	= 1'b1		;
		#30	i_en	= 1'b1		;
		#200	i_en	= 1'b0		;
		#30	i_en	= 1'b1		;
		#150 	$finish			;
	end

	initial begin
        $monitor("t=%0t | rst_n=%b i_en=%b | o_count=%d",
                 $time, rst_n, i_en, o_count); 
	end

	initial begin
		$dumpfile ("counter6_down.vcd")	;
		$dumpvars (0, tb_counter6_down)	;
	end

endmodule

1_RTL/2_TINY_PROJECT/counter6_down.vcd
$date
    Jul  9, 2026  04:33:33
$end
$version
    TOOL:	xmsim(64)	22.03-s012
$end
$timescale
    1 ps
$end

$scope module tb_counter6_down $end
$var reg       1 !    clk $end
$var reg       1 "    rst_n $end
$var reg       1 #    i_en $end
$var wire      3 $    o_count [2:0] $end

$scope module dut $end
$var wire      1 %    clk  $end
$var wire      1 &    rst_n  $end
$var wire      1 '    i_en  $end
$var reg       3 (    o_count [2:0] $end
$upscope $end

$upscope $end

$enddefinitions $end
$dumpvars
0!
0"
0#
bx $
0%
0&
0'
bx (
$end
#5000
1!
1%
b101 (
b101 $
#10000
0!
0%
#15000
1!
1%
#20000
1"
0!
0%
1&
#25000
1!
1%
#30000
0!
0%
#35000
1!
1%
#40000
0!
0%
#45000
1!
1%
#50000
1#
0!
0%
1'
#55000
1!
1%
b100 (
b100 $
#60000
0!
0%
#65000
1!
1%
b11 (
b11 $
#70000
0!
0%
#75000
1!
1%
b10 (
b10 $
#80000
0!
0%
#85000
1!
1%
b1 (
b1 $
#90000
0!
0%
#95000
1!
1%
b0 (
b0 $
#100000
0!
0%
#105000
1!
1%
b101 (
b101 $
#110000
0!
0%
#115000
1!
1%
b100 (
b100 $
#120000
0!
0%
#125000
1!
1%
b11 (
b11 $
#130000
0!
0%
#135000
1!
1%
b10 (
b10 $
#140000
0!
0%
#145000
1!
1%
b1 (
b1 $
#150000
0!
0%
#155000
1!
1%
b0 (
b0 $
#160000
0!
0%
#165000
1!
1%
b101 (
b101 $
#170000
0!
0%
#175000
1!
1%
b100 (
b100 $
#180000
0!
0%
#185000
1!
1%
b11 (
b11 $
#190000
0!
0%
#195000
1!
1%
b10 (
b10 $
#200000
0!
0%
#205000
1!
1%
b1 (
b1 $
#210000
0!
0%
#215000
1!
1%
b0 (
b0 $
#220000
0!
0%
#225000
1!
1%
b101 (
b101 $
#230000
0!
0%
#235000
1!
1%
b100 (
b100 $
#240000
0!
0%
#245000
1!
1%
b11 (
b11 $
#250000
0#
0!
0%
0'
#255000
1!
1%
#260000
0!
0%
#265000
1!
1%
#270000
0!
0%
#275000
1!
1%
#280000
1#
0!
0%
1'
#285000
1!
1%
b10 (
b10 $
#290000
0!
0%
#295000
1!
1%
b1 (
b1 $
#300000
0!
0%
#305000
1!
1%
b0 (
b0 $
#310000
0!
0%
#315000
1!
1%
b101 (
b101 $
#320000
0!
0%
#325000
1!
1%
b100 (
b100 $
#330000
0!
0%
#335000
1!
1%
b11 (
b11 $
#340000
0!
0%
#345000
1!
1%
b10 (
b10 $
#350000
0!
0%
#355000
1!
1%
b1 (
b1 $
#360000
0!
0%
#365000
1!
1%
b0 (
b0 $
#370000
0!
0%
#375000
1!
1%
b101 (
b101 $
#380000
0!
0%
#385000
1!
1%
b100 (
b100 $
#390000
0!
0%
#395000
1!
1%
b11 (
b11 $
#400000
0!
0%
#405000
1!
1%
b10 (
b10 $
#410000
0!
0%
#415000
1!
1%
b1 (
b1 $
#420000
0!
0%
#425000
1!
1%
b0 (
b0 $
